gymnasium_planar_robotics/__init__.py
gymnasium_planar_robotics/envs/__init__.py
gymnasium_planar_robotics/envs/basic_envs.py
gymnasium_planar_robotics/envs/manipulation/__init__.py
gymnasium_planar_robotics/envs/manipulation/benchmark_pushing_env.py
gymnasium_planar_robotics/envs/planning/__init__.py
gymnasium_planar_robotics/envs/planning/benchmark_planning_env.py
gymnasium_planar_robotics/utils/__init__.py
gymnasium_planar_robotics/utils/geometry_2D_utils.py
gymnasium_planar_robotics/utils/impedance_control.py
gymnasium_planar_robotics/utils/mujoco_utils.py
gymnasium_planar_robotics/utils/rendering.py
gymnasium_planar_robotics/utils/rotations_utils.py
gymnasium_planar_robotics-1.1.0.dist-info/licenses/LICENSE
gymnasium_planar_robotics-1.1.0.dist-info/METADATA
gymnasium_planar_robotics-1.1.0.dist-info/WHEEL
gymnasium_planar_robotics-1.1.0.dist-info/entry_points.txt
gymnasium_planar_robotics-1.1.0.dist-info/top_level.txt
gymnasium_planar_robotics-1.1.0.dist-info/RECORD
